<?xml version="1.0" encoding="UTF-8"?>
<node name='InternetGatewayDevice' rw='0' type='node'>
    <node name='DeviceSummary' rw='0' getc='0' noc='0' nocc='' acl='Subscriber' type='string'></node>
    <node name='LANDeviceNumberOfEntries' rw='0' getc='0' noc='0' nocc='' acl='' type='unsignedInt'></node>
    <node name='WANDeviceNumberOfEntries' rw='0' getc='0' noc='0' nocc='' acl='' type='unsignedInt'></node>
    <node name='DeviceInfo' rw='0' type='node'>
        <node name='Manufacturer' rw='0' getc='0' noc='0' nocc='' acl='' type='string'>Richerlink</node>
        <node name='ManufacturerOUI' rw='0' getc='0' noc='0' nocc='' acl='' type='string'>CTCOUI</node>
        <node name='ModelName' rw='0' getc='0' noc='0' nocc='' acl='' type='string'>Agent_5_0</node>
        <node name='Description' rw='0' getc='0' noc='0' nocc='' acl='' type='string'></node>
        <node name='ProductClass' rw='0' getc='0' noc='0' nocc='' acl='' type='string'></node>
        <node name='SerialNumber' rw='0' getc='0' noc='0' nocc='' acl='' type='string'>AABBCCDDEEFF</node>
        <node name='HardwareVersion' rw='0' getc='0' noc='0' nocc='' acl='' type='string'></node>
        <node name='SoftwareVersion' rw='0' getc='0' noc='0' nocc='' acl='' type='string'></node>
        <node name='SpecVersion' rw='0' getc='0' noc='0' nocc='' acl='' type='string'>1.0</node>
        <node name='ProvisioningCode' rw='1' getc='0' noc='0' nocc='' acl='' type='string'>WKSS</node>
        <node name='UpTime' rw='0' getc='0' noc='0' nocc='' acl='' type='unsignedInt'></node>
        <node name='DeviceLog' rw='0' getc='0' noc='0' nocc='' acl='' type='string'></node>
        <node name='X_CT-COM_TeleComAccount' rw='0' type='node'>
            <node name='Password' rw='1' getc='0' noc='0' nocc='' acl='Subscriber' type='string'></node>      
            <node name='UserName' rw='1' getc='0' noc='0' nocc='' acl='Subscriber' type='string'></node>
            <node name='Enable' rw='1' getc='0' noc='0' nocc='' acl='Subscriber' type='boolean'></node>
        </node>
        <node name='X_CT-COM_PortalManagement' rw='0' type='node'>
            <node name='Enable' rw='1' getc='0' noc='0' nocc='' acl='Subscriber' type='boolean'></node>
            <node name='PortalUrl-Computer' rw='1' getc='0' noc='0' nocc='' acl='Subscriber' type='string'></node>     
            <node name='PortalUrl-STB' rw='1' getc='0' noc='0' nocc='' acl='Subscriber' type='string'></node>
            <node name='PortalUrl-Phone' rw='1' getc='0' noc='0' nocc='' acl='Subscriber' type='string'></node>                       
        </node>
	    <node name='X_CT-COM_ALGAbility' rw='0' type='node'>
	        <node name='H323Enable' rw='1' getc='0' noc='0' nocc='' acl='Subscriber' type='boolean'></node>
                <!--
	        <node name='SIPEnable' rw='1' getc='0' noc='0' nocc='' acl='Subscriber' type='boolean'></node>
                -->	        
		<node name='RTSPEnable' rw='1' getc='0' noc='0' nocc='' acl='Subscriber' type='boolean'></node>
	        <node name='L2TPEnable' rw='1' getc='0' noc='0' nocc='' acl='Subscriber' type='boolean'></node>
	        <node name='IPSECEnable' rw='1' getc='0' noc='0' nocc='' acl='Subscriber' type='boolean'></node>
	        <node name='FTPEnable' rw='1' getc='0' noc='0' nocc='' acl='Subscriber' type='boolean'></node>            
	    </node>
        <!--
        <node name='X_CT-COM_UPNP' rw='0' type='node'>
            <node name='Enable' rw='1' getc='0' noc='0' nocc='' acl='Subscriber' type='boolean'></node>
        </node>
        -->
        <node name='X_CT-COM_ReConnect' rw='0' type='node'>
            <node name='Enable' rw='1' getc='0' noc='0' nocc='' acl='Subscriber' type='boolean'></node>
        </node>
	    <node name='X_CT-COM_ServiceManage' rw='0' type='node'>
	        <node name='TelnetEnable' rw='1' getc='0' noc='0' nocc='' acl='Subscriber' type='boolean'></node>
	        <node name='TelnetUserName' rw='1' getc='0' noc='0' nocc='' acl='Subscriber' type='string'></node>
	        <node name='TelnetPassword' rw='1' getc='1' noc='0' nocc='' acl='Subscriber' type='string'></node>
	        <node name='TelnetPort' rw='1' getc='0' noc='0' nocc='' acl='Subscriber' type='unsignedInt'></node>
	    </node>
	    <node name='X_CT-COM_Alarm' rw='0' type='node'>
	        <node name='Enable' rw='1' getc='0' noc='0' nocc='' acl='Subscriber' type='boolean'></node>
	        <node name='AlarmNumberOfEntries' rw='0' getc='0' noc='0' nocc='' acl='' type='unsignedInt'></node>
	        <node name='AlarmConfig' rw='1' nin='1' il='32' type='node'>
	            <node name='template' rw='1' nin='0' il='0' type='node'>
	            	<node name='ParaList' rw='1' getc='0' noc='0' nocc='' acl='Subscriber' type='string'></node>
	            	<node name='Limit-Max' rw='1' getc='0' noc='0' nocc='' acl='Subscriber' type='string'></node>
	            	<node name='Limit-Min' rw='1' getc='0' noc='0' nocc='' acl='Subscriber' type='string'></node>
	            	<node name='TimeList' rw='1' getc='0' noc='0' nocc='' acl='Subscriber' type='string'></node>
	            	<node name='Mode' rw='1' getc='0' noc='0' nocc='' acl='Subscriber' type='unsignedInt'></node>
	            </node>
	        </node>
	    </node>
	    <node name='X_CT-COM_Monitor' rw='0' type='node'>
	        <node name='Enable' rw='1' getc='0' noc='0' nocc='' acl='Subscriber' type='boolean'></node>
	        <node name='MonitorNumberOfEntries' rw='1' getc='0' noc='0' nocc='' acl='Subscriber' type='unsignedInt'></node>
	        <node name='MonitorConfig' rw='1' nin='1' il='32' type='node'>
	            <node name='template' rw='1' nin='0' il='0' type='node'>
	            	<node name='ParaList' rw='1' getc='0' noc='0' nocc='' acl='Subscriber' type='string'></node>
	            	<node name='TimeList' rw='1' getc='0' noc='0' nocc='' acl='Subscriber' type='string'></node>
	            </node>
	        </node>	        
	    </node>
        <node name='X_CT-COM_Syslog' rw='0' type='node'>
            <node name='Enable' rw='1' getc='0' noc='0' nocc='' acl='Subscriber' type='boolean'></node>
            <node name='Level' rw='1' getc='0' noc='0' nocc='' acl='Subscriber' type='unsignedInt'></node>
        </node>
        <node name='X_CT-COM_Ping' rw='0' type='node'>        
            <node name='Enable' rw='1' getc='0' noc='0' nocc='' acl='Subscriber' type='string'>false</node>
            <node name='PingNumberOfEntries' rw='0' getc='0' noc='0' nocc='' acl='' type='unsignedInt'>3</node>
            <node name='PingConfig' rw='1' nin='1' il='4' type='node'>
                <node name='template' rw='1' nin='0' il='0' type='node'>
                    <node name='DiagnosticsState' rw='1' getc='0' noc='0' nocc='' acl='Subscriber' type='string'>None</node>
                    <node name='Interface' rw='1' getc='0' noc='0' nocc='' acl='Subscriber' type='string'></node>
                    <node name='Host' rw='1' getc='0' noc='0' nocc='' acl='Subscriber' type='string'></node>
                    <node name='NumberOfRepetitions' rw='1' getc='0' noc='0' nocc='' acl='Subscriber' type='unsignedInt'></node>
                    <node name='Timeout' rw='1' getc='0' noc='0' nocc='' acl='Subscriber' type='unsignedInt'></node>
                    <node name='DataBlockSize' rw='1' getc='0' noc='0' nocc='' acl='Subscriber' type='unsignedInt'></node>
                    <node name='DSCP' rw='1' getc='0' noc='0' nocc='' acl='Subscriber' type='unsignedInt'></node>
                    <node name='Interval' rw='1' getc='0' noc='0' nocc='' acl='Subscriber' type='unsignedInt'></node>
                    <node name='Stop' rw='1' getc='0' noc='0' nocc='' acl='Subscriber' type='boolean'></node>
                </node>
            </node>     
        </node>
    </node>
    <node name='ManagementServer' rw='0' type='node'>
        <node name='URL' rw='1' getc='0' noc='0' nocc='' acl='Subscriber' type='string'>http://10.10.1.48:80/comserver/node1/tr069</node>
        <node name='Username' rw='1' getc='0' noc='0' nocc='' acl='Subscriber' type='string'></node>
        <node name='Password' rw='1' getc='1' noc='0' nocc='' acl='Subscriber' type='string'></node>
        <node name='PeriodicInformEnable' rw='1' getc='0' noc='0' nocc='' acl='Subscriber' type='boolean'>True</node>
        <node name='PeriodicInformInterval' rw='1' getc='0' noc='0' nocc='' acl='Subscriber' type='unsignedInt'>30</node>
        <node name='PeriodicInformTime' rw='1' getc='0' noc='0' nocc='' acl='Subscriber' type='dateTime'>0000-00-00T00:00:00</node>
        <node name='ParameterKey' rw='0' getc='0' noc='0' nocc='' acl='Subscriber' type='string'></node>
        <node name='ConnectionRequestURL' rw='0' getc='0' noc='0' nocc='' acl='Subscriber' type='string'>http://172.31.0.37:7547/</node>
        <node name='ConnectionRequestUsername' rw='1' getc='0' noc='0' nocc='' acl='Subscriber' type='string'>admin</node>
        <node name='ConnectionRequestPassword' rw='1' getc='1' noc='0' nocc='' acl='Subscriber' type='string'>admin</node>
        <node name='UpgradesManaged' rw='1' getc='0' noc='0' nocc='' acl='Subscriber' type='boolean'></node>
    </node>
    <node name='Layer3Forwarding' rw='0' type='node'>
        <node name='DefaultConnectionService' rw='1' getc='0' noc='0' nocc='' acl='Subscriber' type='string'></node>
        <node name='ForwardNumberOfEntries' rw='0' getc='0' noc='0' nocc='' acl='' type='unsignedInt'></node>
        <node name='Forwarding' rw='1' nin='1' il='9' type='node'>
            <node name='template' rw='1' nin='0' il='0' type='node'>
                <node name='Enable' rw='1' getc='0' noc='0' nocc='' acl='Subscriber' type='boolean'>False</node>
                <node name='Status' rw='0' getc='0' noc='0' nocc='' acl='' type='string'>Disabled</node>
                <node name='Type' rw='1' getc='0' noc='0' nocc='' acl='Subscriber' type='string'>Host</node>
                <node name='DestIPAddress' rw='1' getc='0' noc='0' nocc='' acl='Subscriber' type='string'></node>
                <node name='DestSubnetMask' rw='1' getc='0' noc='0' nocc='' acl='Subscriber' type='string'></node>
                <node name='SourceIPAddress' rw='1' getc='0' noc='0' nocc='' acl='Subscriber' type='string'></node>
                <node name='SourceSubnetMask' rw='1' getc='0' noc='0' nocc='' acl='Subscriber' type='string'></node>
                <node name='GatewayIPAddress' rw='1' getc='0' noc='0' nocc='' acl='Subscriber' type='string'></node>
                <node name='Interface' rw='1' getc='0' noc='0' nocc='' acl='Subscriber' type='string'></node>
                <node name='ForwardingMetric' rw='1' getc='0' noc='0' nocc='' acl='Subscriber' type='int'>-1</node>
            </node>
        </node>
    </node>
    <node name='LANConfigSecurity' rw='0' type='node'>
        <node name='ConfigPassword' rw='1' getc='1' noc='0' nocc='' acl='Subscriber' type='string'></node>
    </node>
    <node name='LANDevice' rw='1' nin='1' il='1' type='node'>
        <node name='1' rw='0' type='node'>
            <node name='LANEthernetInterfaceNumberOfEntries' rw='0' getc='0' noc='0' nocc='' acl='' type='unsignedInt'>0</node>
            <node name='LANEthernetInterfaceConfig' rw='0' type='node'>
                <node name='1' rw='0' type='node'>
                    <node name='Enable' rw='1' getc='0' noc='0' nocc='' acl='Subscriber' type='boolean'></node>
                    <node name='Status' rw='0' getc='0' noc='0' nocc='' acl='' type='string'></node>
                    <node name='MACAddress' rw='0' getc='0' noc='0' nocc='' acl='' type='string'></node>
                    <node name='MACAddressControlEnabled' rw='1' getc='0' noc='0' nocc='' acl='Subscriber' type='boolean'></node>
                    <node name='MaxBitRate' rw='1' getc='0' noc='0' nocc='' acl='Subscriber' type='string'></node>
                    <node name='DuplexMode' rw='1' getc='0' noc='0' nocc='' acl='Subscriber' type='string'></node>
                    <node name='Stats' rw='0' type='node'>
                        <node name='BytesSent' rw='0' getc='0' noc='0' nocc='' acl='' type='unsignedInt'></node>
                        <node name='BytesReceived' rw='0' getc='0' noc='0' nocc='' acl='' type='unsignedInt'></node>
                        <node name='PacketsSent' rw='0' getc='0' noc='0' nocc='' acl='' type='unsignedInt'></node>
                        <node name='PacketsReceived' rw='0' getc='0' noc='0' nocc='' acl='' type='unsignedInt'></node>
                    </node>
                </node>
                <node name='2' rw='0' type='node'>
                    <node name='Enable' rw='1' getc='0' noc='0' nocc='' acl='Subscriber' type='boolean'></node>
                    <node name='Status' rw='0' getc='0' noc='0' nocc='' acl='' type='string'></node>
                    <node name='MACAddress' rw='0' getc='0' noc='0' nocc='' acl='' type='string'></node>
                    <node name='MACAddressControlEnabled' rw='1' getc='0' noc='0' nocc='' acl='Subscriber' type='boolean'></node>
                    <node name='MaxBitRate' rw='1' getc='0' noc='0' nocc='' acl='Subscriber' type='string'></node>
                    <node name='DuplexMode' rw='1' getc='0' noc='0' nocc='' acl='Subscriber' type='string'></node>
                    <node name='Stats' rw='0' type='node'>
                        <node name='BytesSent' rw='0' getc='0' noc='0' nocc='' acl='' type='unsignedInt'></node>
                        <node name='BytesReceived' rw='0' getc='0' noc='0' nocc='' acl='' type='unsignedInt'></node>
                        <node name='PacketsSent' rw='0' getc='0' noc='0' nocc='' acl='' type='unsignedInt'></node>
                        <node name='PacketsReceived' rw='0' getc='0' noc='0' nocc='' acl='' type='unsignedInt'></node>
                    </node>
                </node>
                <node name='3' rw='0' type='node'>
                    <node name='Enable' rw='1' getc='0' noc='0' nocc='' acl='Subscriber' type='boolean'></node>
                    <node name='Status' rw='0' getc='0' noc='0' nocc='' acl='' type='string'></node>
                    <node name='MACAddress' rw='0' getc='0' noc='0' nocc='' acl='' type='string'></node>
                    <node name='MACAddressControlEnabled' rw='1' getc='0' noc='0' nocc='' acl='Subscriber' type='boolean'></node>
                    <node name='MaxBitRate' rw='1' getc='0' noc='0' nocc='' acl='Subscriber' type='string'></node>
                    <node name='DuplexMode' rw='1' getc='0' noc='0' nocc='' acl='Subscriber' type='string'></node>
                    <node name='Stats' rw='0' type='node'>
                        <node name='BytesSent' rw='0' getc='0' noc='0' nocc='' acl='' type='unsignedInt'></node>
                        <node name='BytesReceived' rw='0' getc='0' noc='0' nocc='' acl='' type='unsignedInt'></node>
                        <node name='PacketsSent' rw='0' getc='0' noc='0' nocc='' acl='' type='unsignedInt'></node>
                        <node name='PacketsReceived' rw='0' getc='0' noc='0' nocc='' acl='' type='unsignedInt'></node>
                    </node>
                </node>
                <node name='4' rw='0' type='node'>
                    <node name='Enable' rw='1' getc='0' noc='0' nocc='' acl='Subscriber' type='boolean'></node>
                    <node name='Status' rw='0' getc='0' noc='0' nocc='' acl='' type='string'></node>
                    <node name='MACAddress' rw='0' getc='0' noc='0' nocc='' acl='' type='string'></node>
                    <node name='MACAddressControlEnabled' rw='1' getc='0' noc='0' nocc='' acl='Subscriber' type='boolean'></node>
                    <node name='MaxBitRate' rw='1' getc='0' noc='0' nocc='' acl='Subscriber' type='string'></node>
                    <node name='DuplexMode' rw='1' getc='0' noc='0' nocc='' acl='Subscriber' type='string'></node>
                    <node name='Stats' rw='0' type='node'>
                        <node name='BytesSent' rw='0' getc='0' noc='0' nocc='' acl='' type='unsignedInt'></node>
                        <node name='BytesReceived' rw='0' getc='0' noc='0' nocc='' acl='' type='unsignedInt'></node>
                        <node name='PacketsSent' rw='0' getc='0' noc='0' nocc='' acl='' type='unsignedInt'></node>
                        <node name='PacketsReceived' rw='0' getc='0' noc='0' nocc='' acl='' type='unsignedInt'></node>
                    </node>
                </node>
            </node>
            <node name='LANHostConfigManagement' rw='0' type='node'>
                <node name='DHCPServerConfigurable' rw='1' getc='0' noc='0' nocc='' acl='Subscriber' type='boolean'>True</node>
                <node name='DHCPServerEnable' rw='1' getc='0' noc='0' nocc='' acl='Subscriber' type='boolean'>False</node>
                <node name='DHCPRelay' rw='0' getc='0' noc='0' nocc='' acl='' type='boolean'></node>
                <node name='MinAddress' rw='0' getc='0' noc='0' nocc='' acl='' type='string'></node>
                <node name='MaxAddress' rw='0' getc='0' noc='0' nocc='' acl='' type='string'></node>
                <node name='ReservedAddresses' rw='1' getc='0' noc='0' nocc='' acl='Subscriber' type='string'></node>
                <node name='SubnetMask' rw='1' getc='0' noc='0' nocc='' acl='Subscriber' type='string'></node>
                <node name='DNSServers' rw='1' getc='0' noc='0' nocc='' acl='Subscriber' type='string'></node>
                <node name='DomainName' rw='1' getc='0' noc='0' nocc='' acl='Subscriber' type='string'></node>
                <node name='IPRouters' rw='1' getc='0' noc='0' nocc='' acl='Subscriber' type='string'></node>
                <node name='DHCPLeaseTime' rw='1' getc='0' noc='0' nocc='' acl='Subscriber' type='int'>86400</node>
                <node name='UseAllocatedWAN' rw='1' getc='0' noc='0' nocc='' acl='Subscriber' type='string'>Normal</node>
                <node name='AssociatedConnection' rw='1' getc='0' noc='0' nocc='' acl='Subscriber' type='string'></node>
                <node name='PassthroughLease' rw='1' getc='0' noc='0' nocc='' acl='Subscriber' type='unsignedInt'>600</node>
                <node name='PassthroughMACAddress' rw='1' getc='0' noc='0' nocc='' acl='Subscriber' type='string'></node>
                <node name='AllowedMACAddresses' rw='1' getc='0' noc='0' nocc='' acl='Subscriber' type='string'></node>
                <node name='IPInterfaceNumberOfEntries' rw='0' getc='0' noc='0' nocc='' acl='' type='unsignedInt'>0</node>
        	    <node name='X_CT-COM_STB-MinAddress' rw='1' getc='0' noc='0' nocc='' acl='Subscriber' type='string'></node>
        	    <node name='X_CT-COM_STB-MaxAddress' rw='1' getc='0' noc='0' nocc='' acl='Subscriber' type='string'></node>
        	    <node name='X_CT-COM_Phone-MinAddress' rw='1' getc='0' noc='0' nocc='' acl='Subscriber' type='string'></node>
        	    <node name='X_CT-COM_Phone-MaxAddress' rw='1' getc='0' noc='0' nocc='' acl='Subscriber' type='string'></node>
        	    <node name='X_CT-COM_Camera-MinAddress' rw='1' getc='0' noc='0' nocc='' acl='Subscriber' type='string'></node>
        	    <node name='X_CT-COM_Camera-MaxAddress' rw='1' getc='0' noc='0' nocc='' acl='Subscriber' type='string'></node>
        	    <node name='X_CT-COM_Computer-MinAddress' rw='1' getc='0' noc='0' nocc='' acl='Subscriber' type='string'></node>
        	    <node name='X_CT-COM_Computer-MaxAddress' rw='1' getc='0' noc='0' nocc='' acl='Subscriber' type='string'></node> 
                <node name='IPInterface' rw='1' nin='1' il='9' type='node'>
                    <node name='1' rw='1' type='node'>
                        <node name='Enable' rw='1' getc='0' noc='0' nocc='' acl='Subscriber' type='boolean'>False</node>
                        <node name='IPInterfaceIPAddress' rw='1' getc='0' noc='0' nocc='' acl='Subscriber' type='string'></node>
                        <node name='IPInterfaceSubnetMask' rw='1' getc='0' noc='0' nocc='' acl='Subscriber' type='string'></node>
                        <node name='IPInterfaceAddressingType' rw='1' getc='0' noc='0' nocc='' acl='Subscriber' type='string'>DHCP</node>
                    </node>
                </node>
            </node>
            <node name='Hosts' rw='0' type='node'>
                <node name='HostNumberOfEntries' rw='0' getc='0' noc='0' nocc='' acl='' type='unsignedInt'></node>
                 <node name='Host' rw='1' nin='1' il='128' type='node' dynamic='1'>
                    <node name='template' rw='1' nin='0' il='0' type='node'>
                        <node name='IPAddress' rw='0' getc='0' noc='0' nocc='' acl='' type='string'></node>
                        <node name='AddressSource' rw='0' getc='0' noc='0' nocc='' acl='' type='string'></node>
                        <node name='LeaseTimeRemaining' rw='0' getc='0' noc='0' nocc='' acl='' type='int'></node>
                        <node name='MACAddress' rw='0' getc='0' noc='0' nocc='' acl='' type='string'></node>
                        <node name='HostName' rw='0' getc='0' noc='0' nocc='' acl='' type='string'></node>
                        <node name='InterfaceType' rw='0' getc='0' noc='0' nocc='' acl='' type='string'></node>
                        <node name='Active' rw='0' getc='0' noc='0' nocc='' acl='' type='boolean'></node>
                    </node>
                </node>
            </node>
            <node name='WLANConfiguration' rw='1' nin='1' il='4' type='node'>
                <node name='template' rw='1' nin='0' il='0' type='node'>
                    <node name='Enable' rw='1' getc='0' noc='0' nocc='' acl='Subscriber' type='boolean'></node>
                    <node name='Status' rw='0' getc='0' noc='0' nocc='' acl='' type='string'></node>
                    <node name='BSSID' rw='0' getc='0' noc='0' nocc='' acl='' type='string'></node>
                    <node name='MaxBitRate' rw='1' getc='0' noc='0' nocc='' acl='' type='string'></node>
                    <node name='Channel' rw='1' getc='0' noc='0' nocc='' acl='Subscriber' type='unsignedInt'></node>
                    <node name='ChannelsInUse' rw='0' getc='0' noc='0' nocc='' acl='' type='unsignedInt'></node>
                    <node name='SSID' rw='1' getc='0' noc='0' nocc='' acl='Subscriber' type='string'></node>
                    <node name='BeaconType' rw='1' getc='0' noc='0' nocc='' acl='Subscriber' type='string'></node>
                    <node name='MACAddressControlEnabled' rw='1' getc='0' noc='0' nocc='' acl='Subscriber' type='boolean'></node>
                    <node name='Standard' rw='1' getc='0' noc='0' nocc='' acl='Subscriber' type='string'></node>
                    <node name='WEPKeyIndex' rw='1' getc='0' noc='0' nocc='' acl='Subscriber' type='unsignedInt'></node>
                    <node name='KeyPassphrase' rw='1' getc='0' noc='0' nocc='' acl='Subscriber' type='string'></node>
                    <node name='WEPEncryptionLevel' rw='1' getc='0' noc='0' nocc='' acl='Subscriber' type='string'></node>
                    <node name='BasicEncryptionModes' rw='1' getc='0' noc='0' nocc='' acl='Subscriber' type='string'></node>
                    <node name='BasicAuthenticationMode' rw='1' getc='0' noc='0' nocc='' acl='Subscriber' type='string'></node>
                    <node name='WPAEncryptionModes' rw='1' getc='0' noc='0' nocc='' acl='Subscriber' type='string'></node>
                    <node name='WPAAuthenticationMode' rw='1' getc='0' noc='0' nocc='' acl='Subscriber' type='string'></node>
                    <node name='PossibleChannels' rw='1' getc='0' noc='0' nocc='' acl='Subscriber' type='string'></node>
                    <!--
                    <node name='BasicDataTransmitRates' rw='1' getc='0' noc='0' nocc='' acl='Subscriber' type='string'></node>
                    <node name='OperationalDataTransmitRates' rw='1' getc='0' noc='0' nocc='' acl='Subscriber' type='string'></node>
                    <node name='PossibleDataTransmitRates' rw='1' getc='0' noc='0' nocc='' acl='Subscriber' type='string'></node>
                    -->
                    <node name='RadioEnabled' rw='1' getc='0' noc='0' nocc='' acl='Subscriber' type='boolean'></node>
                    <node name='AutoRateFallBackEnabled' rw='1' getc='0' noc='0' nocc='' acl='Subscriber' type='boolean'></node>
                    <node name='TotalBytesSent' rw='0' getc='0' noc='0' nocc='' acl='' type='unsignedInt'></node>
                    <node name='TotalBytesReceived' rw='0' getc='0' noc='0' nocc='' acl='' type='unsignedInt'></node>
                    <node name='TotalPacketsSent' rw='0' getc='0' noc='0' nocc='' acl='' type='unsignedInt'></node>
                    <node name='TotalPacketsReceived' rw='0' getc='0' noc='0' nocc='' acl='' type='unsignedInt'></node>
                    <node name='TotalAssociations' rw='1' nin='0' il='0' type='unsignedInt'></node>
                    <node name='AssociatedDevice' rw='1' nin='1' il='128' type='node' dynamic='1'>
                    	<node name='template' rw='1' nin='0' il='0' type='node'>
	                    	<node name='AssociatedDeviceMACAddress' rw='0' getc='0' noc='0' nocc='' acl='' type='string'></node>
	                    	<node name='AssociatedDeviceIPAddress' rw='0' getc='0' noc='0' nocc='' acl='' type='string'></node>
	                    	<node name='AssociatedDeviceAuthenticationState' rw='0' getc='0' noc='0' nocc='' acl='' type='string'></node>
                    	 </node>
                    </node>  
                    <node name='WEPKey' rw='1' nin='0' il='4' type='node'>
                    	<node name='1' rw='0' type='node'>
                    		<node name='WEPKey' rw='1' getc='0' noc='0' nocc='' acl='' type='string'></node>
                    	</node>
                    	<node name='2' rw='0' type='node'>
                    		<node name='WEPKey' rw='1' getc='0' noc='0' nocc='' acl='' type='string'></node>
                    	</node>  
                    	<node name='3' rw='0' type='node'>
                    		<node name='WEPKey' rw='1' getc='0' noc='0' nocc='' acl='' type='string'></node>
                    	</node>	 
                    	<node name='4' rw='0' type='node'>
                    		<node name='WEPKey' rw='1' getc='0' noc='0' nocc='' acl='' type='string'></node>
                    	</node>	                    	                   	                  	
                    </node>  
                    <node name='PreSharedKey' rw='1' nin='0' il='1' type='node'>
                        <node name='1' rw='0' type='node'>
	            			<node name='PreSharedKey' rw='1' getc='0' noc='0' nocc='' acl='' type='string'></node>
	            		</node>
                    </node>
                    <node name='X_CT-COM_SSIDHide' rw='1' getc='0' noc='0' nocc='' acl='Subscriber' type='boolean'></node>
                    <node name='X_CT-COM_RFBand' rw='1' getc='0' noc='0' nocc='' acl='Subscriber' type='string'></node>
                    <node name='X_CT-COM_ChannelWidth' rw='1' getc='0' noc='0' nocc='' acl='Subscriber' type='string'></node>
                    <node name='X_CT-COM_GuardInterval' rw='1' getc='0' noc='0' nocc='' acl='Subscriber' type='string'></node>
                    <!--<node name='X_CT-COM_RetryTimeout' rw='1' getc='0' noc='0' nocc='' acl='Subscriber' type='string'></node>-->
                    <node name='X_CT-COM_Powerlevel' rw='1' getc='0' noc='0' nocc='' acl='Subscriber' type='unsignedInt'></node>
                    <node name='X_CT-COM_PowerValue' rw='0' getc='0' noc='0' nocc='' acl='' type='unsignedInt'></node>
                    <node name='X_CT-COM_APModuleEnable' rw='1' getc='0' noc='0' nocc='' acl='Subscriber' type='boolean'></node>
                    <node name='X_CT-COM_WPSKeyWord' rw='0' getc='0' noc='0' nocc='' acl='Subscriber' type='string'></node>                    
                </node>
            </node>
        </node>
    </node>
    <node name='WANDevice' rw='0' type='node'>
        <node name='1' rw='0' type='node'>
            <node name='WANConnectionNumberOfEntries' rw='0' getc='0' noc='0' nocc='' acl='' type='unsignedInt'></node>
            <node name='WANCommonInterfaceConfig' rw='0' type='node'>
                <node name='EnabledForInternet' rw='1' getc='0' noc='0' nocc='' acl='Subscriber' type='boolean'></node>
                <node name='WANAccessType' rw='0' getc='0' noc='0' nocc='' acl='' type='string'></node>
                <node name='Layer1UpstreamMaxBitRate' rw='0' getc='0' noc='0' nocc='' acl='' type='unsignedInt'></node>
                <node name='Layer1DownstreamMaxBitRate' rw='0' getc='0' noc='0' nocc='' acl='' type='unsignedInt'></node>
                <node name='PhysicalLinkStatus' rw='0' getc='0' noc='0' nocc='' acl='' type='string'></node>
                <node name='TotalBytesSent' rw='0' getc='0' noc='0' nocc='' acl='' type='unsignedInt'></node>
                <node name='TotalBytesReceived' rw='0' getc='0' noc='0' nocc='' acl='' type='unsignedInt'></node>
                <node name='TotalPacketsSent' rw='0' getc='0' noc='0' nocc='' acl='' type='unsignedInt'></node>
                <node name='TotalPacketsReceived' rw='0' getc='0' noc='0' nocc='' acl='' type='unsignedInt'></node>
            </node>
            <node name='WANConnectionDevice' rw='1' nin='1' il='8' type='node'>
                <node name='template' rw='1' nin='0' il='0' type='node'>
                    <node name='WANIPConnectionNumberOfEntries' rw='0' getc='0' noc='0' nocc='' acl='' type='unsignedInt'></node>
                    <node name='WANPPPConnectionNumberOfEntries' rw='0' getc='0' noc='0' nocc='' acl='' type='unsignedInt'></node>
                    <node name='WANIPConnection' rw='1' nin='1' il='1' type='node'>
                        <node name='template' rw='1' nin='0' il='0' type='node'>
                            <node name='Enable' rw='1' getc='0' noc='0' nocc='' acl='Subscriber' type='boolean'>False</node>
                            <node name='ConnectionStatus' rw='0' getc='0' noc='0' nocc='' acl='' type='string'></node>
                            <node name='PossibleConnectionTypes' rw='0' getc='0' noc='0' nocc='' acl='' type='string'></node>
                            <node name='ConnectionType' rw='1' getc='0' noc='0' nocc='' acl='Subscriber' type='string'></node>
                            <node name='Name' rw='1' getc='0' noc='0' nocc='' acl='Subscriber' type='string'></node>
                            <node name='Uptime' rw='0' getc='0' noc='0' nocc='' acl='' type='unsignedInt'></node>
                            <node name='LastConnectionError' rw='0' getc='0' noc='0' nocc='' acl='' type='string'>ERROR_NONE</node>
                            <node name='RSIPAvailable' rw='0' getc='0' noc='0' nocc='' acl='' type='boolean'></node>
                            <node name='NATEnabled' rw='1' getc='0' noc='0' nocc='' acl='Subscriber' type='boolean'></node>
                            <node name='AddressingType' rw='1' getc='0' noc='0' nocc='' acl='Subscriber' type='string'></node>
                            <node name='ExternalIPAddress' rw='1' getc='0' noc='0' nocc='' acl='Subscriber' type='string'></node>
                            <node name='SubnetMask' rw='1' getc='0' noc='0' nocc='' acl='Subscriber' type='string'></node>
                            <node name='DefaultGateway' rw='1' getc='0' noc='0' nocc='' acl='Subscriber' type='string'></node>
                            <node name='DNSEnabled' rw='1' getc='0' noc='0' nocc='' acl='Subscriber' type='boolean'>True</node>
                            <node name='DNSOverrideAllowed' rw='1' getc='0' noc='0' nocc='' acl='Subscriber' type='boolean'>False</node>
                            <node name='DNSServers' rw='1' getc='0' noc='0' nocc='' acl='Subscriber' type='string'></node>
                            <node name='MACAddress' rw='1' getc='0' noc='0' nocc='' acl='Subscriber' type='string'></node>
                            <node name='ConnectionTrigger' rw='1' getc='0' noc='0' nocc='' acl='Subscriber' type='string'>OnDemand</node>
                            <node name='RouteProtocolRx' rw='1' getc='0' noc='0' nocc='' acl='Subscriber' type='string'>Off</node>
                            <node name='PortMappingNumberOfEntries' rw='0' getc='0' noc='0' nocc='' acl='' type='unsignedInt'></node>
                            <node name='PortMapping' rw='1' nin='1' il='9' type='node'>
                                <node name='template' rw='1' nin='0' il='0' type='node'>
                                    <node name='PortMappingEnabled' rw='1' getc='0' noc='0' nocc='' acl='Subscriber' type='boolean'>False</node>
                                    <node name='PortMappingLeaseDuration' rw='1' getc='0' noc='0' nocc='' acl='Subscriber' type='unsignedInt'></node>
                                    <node name='RemoteHost' rw='1' getc='0' noc='0' nocc='' acl='Subscriber' type='string'></node>
                                    <node name='ExternalPort' rw='1' getc='0' noc='0' nocc='' acl='Subscriber' type='unsignedInt'></node>
                                    <node name='InternalPort' rw='1' getc='0' noc='0' nocc='' acl='Subscriber' type='unsignedInt'></node>
                                    <node name='PortMappingProtocol' rw='1' getc='0' noc='0' nocc='' acl='Subscriber' type='string'></node>
                                    <node name='InternalClient' rw='1' getc='0' noc='0' nocc='' acl='Subscriber' type='string'></node>
                                    <node name='PortMappingDescription' rw='1' getc='0' noc='0' nocc='' acl='Subscriber' type='string'></node>
                                </node>
                            </node>
                            <node name='Stats' rw='0' type='node'>
                                <node name='EthernetBytesSent' rw='0' getc='0' noc='0' nocc='' acl='' type='unsignedInt'></node>
                                <node name='EthernetBytesReceived' rw='0' getc='0' noc='0' nocc='' acl='' type='unsignedInt'></node>
                                <node name='EthernetPacketsSent' rw='0' getc='0' noc='0' nocc='' acl='' type='unsignedInt'></node>
                                <node name='EthernetPacketsReceived' rw='0' getc='0' noc='0' nocc='' acl='' type='unsignedInt'></node>
                            </node>
                            <node name='X_CT-COM_LanInterface' rw='1' getc='0' noc='0' nocc='' acl='Subscriber' type='string'></node>
                            <node name='X_CT-COM_ServiceList' rw='1' getc='0' noc='0' nocc='' acl='Subscriber' type='string'></node>
                            <node name='X_CT-COM_LanInterface-DHCPEnable' rw='1' getc='0' noc='0' nocc='' acl='Subscriber' type='boolean'>False</node>
                            <node name='X_CT-COM_MulticastVlan' rw='1' getc='0' noc='0' nocc='' acl='Subscriber' type='int'></node>
                            <node name='X_CT-COM_DDNSConfiguration' rw='1' nin='1' il='9' type='node'>
                            	<node name='template' rw='1' nin='0' il='0' type='node'>
                            	   <node name='DDNSCfgEnabled' rw='1' getc='0' noc='0' nocc='' acl='Subscriber' type='string'></node>
                            	   <node name='DDNSProvider' rw='1' getc='0' noc='0' nocc='' acl='Subscriber' type='string'></node>
                            	   <node name='DDNSUsername' rw='1' getc='0' noc='0' nocc='' acl='Subscriber' type='string'></node>
                                    <node name='DDNSPassword' rw='1' getc='0' noc='0' nocc='' acl='Subscriber' type='string'></node>
                                    <node name='ServicePort' rw='1' getc='0' noc='0' nocc='' acl='Subscriber' type='string'></node>
                                    <node name='DDNSDomainName' rw='1' getc='0' noc='0' nocc='' acl='Subscriber' type='string'></node>
                                    <node name='DDNSHostName' rw='1' getc='0' noc='0' nocc='' acl='Subscriber' type='string'></node>
                            	</node>
                            </node>
                            <node name='X_CT-COM_DHCPOPTION60' rw='1' nin='5' il='9' type='node'>
                                <node name='template' rw='1' nin='0' il='0' type='node'>
                                    <node name='Enable' rw='1' getc='0' noc='0' nocc='' acl='Subscriber' type='boolean'>False</node>
                                    <node name='Type' rw='1' getc='0' noc='0' nocc='' acl='Subscriber' type='unsignedInt'>34</node>
                                    <node name='ValueMode' rw='1' getc='0' noc='0' nocc='' acl='Subscriber' type='string'>0</node>
                                    <node name='Value' rw='1' getc='0' noc='0' nocc='' acl='Subscriber' type='string'>False</node>
                                </node>
                                <node name='4' rw='0' nin='0' il='0' type='node'>
                                    <node name='Enable' rw='1' getc='0' noc='0' nocc='' acl='Subscriber' type='boolean'>False</node>
                                    <node name='Type' rw='1' getc='0' noc='0' nocc='' acl='Subscriber' type='unsignedInt'>34</node>
                                    <node name='ValueMode' rw='1' getc='0' noc='0' nocc='' acl='Subscriber' type='string'>0</node>
                                    <node name='Value' rw='1' getc='0' noc='0' nocc='' acl='Subscriber' type='string'>False</node>
                                </node>   
                                <node name='3' rw='0' nin='0' il='0' type='node'>
                                    <node name='Enable' rw='1' getc='0' noc='0' nocc='' acl='Subscriber' type='boolean'>False</node>
                                    <node name='Type' rw='1' getc='0' noc='0' nocc='' acl='Subscriber' type='unsignedInt'>34</node>
                                    <node name='ValueMode' rw='1' getc='0' noc='0' nocc='' acl='Subscriber' type='string'>0</node>
                                    <node name='Value' rw='1' getc='0' noc='0' nocc='' acl='Subscriber' type='string'>False</node>
                                </node>
                                <node name='2' rw='0' nin='0' il='0' type='node'>
                                    <node name='Enable' rw='1' getc='0' noc='0' nocc='' acl='Subscriber' type='boolean'>False</node>
                                    <node name='Type' rw='1' getc='0' noc='0' nocc='' acl='Subscriber' type='unsignedInt'>34</node>
                                    <node name='ValueMode' rw='1' getc='0' noc='0' nocc='' acl='Subscriber' type='string'>0</node>
                                    <node name='Value' rw='1' getc='0' noc='0' nocc='' acl='Subscriber' type='string'>False</node>
                                </node>
                                <node name='1' rw='0' nin='0' il='0' type='node'>
                                    <node name='Enable' rw='1' getc='0' noc='0' nocc='' acl='Subscriber' type='boolean'>False</node>
                                    <node name='Type' rw='1' getc='0' noc='0' nocc='' acl='Subscriber' type='unsignedInt'>34</node>
                                    <node name='ValueMode' rw='1' getc='0' noc='0' nocc='' acl='Subscriber' type='string'>0</node>
                                    <node name='Value' rw='1' getc='0' noc='0' nocc='' acl='Subscriber' type='string'>False</node>
                                </node>
                            </node>
                            <node name='X_CT-COM_DHCPOPTION125' rw='1' nin='1' il='9' type='node'>
                                <node name='template' rw='1' nin='0' il='0' type='node'>
                                    <node name='Enable' rw='1' getc='0' noc='0' nocc='' acl='Subscriber' type='boolean'>False</node>
                                    <node name='Value' rw='1' getc='0' noc='0' nocc='' acl='Subscriber' type='string'>False</node>
                                </node>
                            </node>
                        </node>
                    </node>
                    <node name='WANPPPConnection' rw='1' nin='1' il='1' type='node'>
                        <node name='template' rw='1' nin='0' il='0' type='node'>
                            <node name='Enable' rw='1' getc='0' noc='0' nocc='' acl='Subscriber' type='boolean'>False</node>
                            <node name='ConnectionStatus' rw='0' getc='0' noc='0' nocc='' acl='' type='string'></node>
                            <node name='PossibleConnectionTypes' rw='0' getc='0' noc='0' nocc='' acl='' type='string'></node>
                            <node name='ConnectionType' rw='1' getc='0' noc='0' nocc='' acl='Subscriber' type='string'></node>
                            <node name='Name' rw='1' getc='0' noc='0' nocc='' acl='Subscriber' type='string'></node>
                            <node name='Uptime' rw='0' getc='0' noc='0' nocc='' acl='' type='unsignedInt'></node>
                            <node name='LastConnectionError' rw='0' getc='0' noc='0' nocc='' acl='' type='string'></node>
                            <node name='RSIPAvailable' rw='0' getc='0' noc='0' nocc='' acl='' type='boolean'></node>
                            <node name='NATEnabled' rw='1' getc='0' noc='0' nocc='' acl='Subscriber' type='boolean'></node>
                            <node name='Username' rw='1' getc='0' noc='0' nocc='' acl='Subscriber' type='string'></node>
                            <node name='Password' rw='1' getc='1' noc='0' nocc='' acl='Subscriber' type='string'></node>
                            <node name='ExternalIPAddress' rw='0' getc='0' noc='0' nocc='' acl='' type='string'></node>
                            <node name='RemoteIPAddress' rw='0' getc='0' noc='0' nocc='' acl='' type='string'></node>
                            <node name='DNSEnabled' rw='1' getc='0' noc='0' nocc='' acl='' type='boolean'>True</node>
                            <node name='DNSOverrideAllowed' rw='1' getc='0' noc='0' nocc='' acl='Subscriber' type='boolean'>False</node>
                            <node name='DNSServers' rw='1' getc='0' noc='0' nocc='' acl='Subscriber' type='string'></node>
                            <node name='MACAddress' rw='1' getc='0' noc='0' nocc='' acl='Subscriber' type='string'></node>
                            <node name='TransportType' rw='0' getc='0' noc='0' nocc='' acl='' type='string'></node>
                            <node name='PPPoEACName' rw='1' getc='0' noc='0' nocc='' acl='Subscriber' type='string'></node>
                            <node name='PPPoEServiceName' rw='1' getc='0' noc='0' nocc='' acl='Subscriber' type='string'></node>
                            <node name='ConnectionTrigger' rw='1' getc='0' noc='0' nocc='' acl='Subscriber' type='string'>OnDemand</node>
                            <node name='RouteProtocolRx' rw='1' getc='0' noc='0' nocc='' acl='Subscriber' type='string'>Off</node>
                            <node name='X_CT-COM_LanInterface' rw='1' getc='0' noc='0' nocc='' acl='Subscriber' type='string'></node>
                            <node name='X_CT-COM_ServiceList' rw='1' getc='0' noc='0' nocc='' acl='Subscriber' type='string'></node>
                            <node name='X_CT-COM_LanInterface-DHCPEnable' rw='1' getc='0' noc='0' nocc='' acl='Subscriber' type='boolean'>False</node>
                            <node name='X_CT-COM_MulticastVlan' rw='1' getc='0' noc='0' nocc='' acl='Subscriber' type='int'></node>
                            <node name='X_CT-COM_ProxyEnable' rw='1' getc='0' noc='0' nocc='' acl='Subscriber' type='boolean'></node>
                            <node name='X_CT-COM_MAXUser' rw='1' getc='0' noc='0' nocc='' acl='Subscriber' type='unsignedInt'></node>                            
                            <node name='PortMappingNumberOfEntries' rw='0' getc='0' noc='0' nocc='' acl='Subscriber' type='unsignedInt'></node>
                            <node name='PortMapping' rw='1' nin='1' il='9' type='node'>
                                <node name='template' rw='1' nin='0' il='0' type='node'>
                                    <node name='PortMappingEnabled' rw='1' getc='0' noc='0' nocc='' acl='Subscriber' type='boolean'>False</node>
                                    <node name='PortMappingLeaseDuration' rw='1' getc='0' noc='0' nocc='' acl='Subscriber' type='unsignedInt'></node>
                                    <node name='RemoteHost' rw='1' getc='0' noc='0' nocc='' acl='Subscriber' type='string'></node>
                                    <node name='ExternalPort' rw='1' getc='0' noc='0' nocc='' acl='Subscriber' type='unsignedInt'></node>
                                    <node name='InternalPort' rw='1' getc='0' noc='0' nocc='' acl='Subscriber' type='unsignedInt'></node>
                                    <node name='PortMappingProtocol' rw='1' getc='0' noc='0' nocc='' acl='Subscriber' type='string'></node>
                                    <node name='InternalClient' rw='1' getc='0' noc='0' nocc='' acl='Subscriber' type='string'></node>
                                    <node name='PortMappingDescription' rw='1' getc='0' noc='0' nocc='' acl='Subscriber' type='string'></node>
                                </node>
                            </node>
                            <node name='Stats' rw='0' type='node'>
                                <node name='EthernetBytesSent' rw='0' getc='0' noc='0' nocc='' acl='' type='unsignedInt'></node>
                                <node name='EthernetBytesReceived' rw='0' getc='0' noc='0' nocc='' acl='' type='unsignedInt'></node>
                                <node name='EthernetPacketsSent' rw='0' getc='0' noc='0' nocc='' acl='' type='unsignedInt'></node>
                                <node name='EthernetPacketsReceived' rw='0' getc='0' noc='0' nocc='' acl='' type='unsignedInt'></node>
                            </node>
                            <node name='X_CT-COM_DDNSConfiguration' rw='1' nin='1' il='9' type='node'>
                            	<node name='template' rw='1' nin='0' il='0' type='node'>
                            	   <node name='DDNSCfgEnabled' rw='1' getc='0' noc='0' nocc='' acl='Subscriber' type='string'></node>
                            	   <node name='DDNSProvider' rw='1' getc='0' noc='0' nocc='' acl='Subscriber' type='string'></node>
                            	   <node name='DDNSUsername' rw='1' getc='0' noc='0' nocc='' acl='Subscriber' type='string'></node>
                                    <node name='DDNSPassword' rw='1' getc='0' noc='0' nocc='' acl='Subscriber' type='string'></node>
                                    <node name='ServicePort' rw='1' getc='0' noc='0' nocc='' acl='Subscriber' type='string'></node>
                                    <node name='DDNSDomainName' rw='1' getc='0' noc='0' nocc='' acl='Subscriber' type='string'></node>
                                    <node name='DDNSHostName' rw='1' getc='0' noc='0' nocc='' acl='Subscriber' type='string'></node>
                            	</node>
                            </node>
                        </node>
                    </node>
                    <node name='WANEthernetLinkConfig' rw='0' type='node'>
                        <node name='EthernetLinkStatus' rw='0' getc='0' noc='0' nocc='' acl='' type='string'></node>
                        <node name='X_CT-COM_Enable' rw='1' getc='0' noc='0' nocc='' acl='Subscriber' type='boolean'></node>
                        <node name='X_CT-COM_Mode' rw='1' getc='0' noc='0' nocc='' acl='Subscriber' type='unsignedInt'></node>
                        <node name='X_CT-COM_VLANIDMark' rw='1' getc='0' noc='0' nocc='' acl='Subscriber' type='int'></node>
                        <node name='X_CT-COM_802-1pMark' rw='1' getc='0' noc='0' nocc='' acl='Subscriber' type='unsignedInt'></node>
                    </node>
                </node>
            </node>
            <node name='WANEthernetInterfaceConfig' rw='0' type='node'>
                <node name='Enable' rw='1' getc='0' noc='0' nocc='' acl='Subscriber' type='boolean'></node>
                <node name='Status' rw='0' getc='0' noc='0' nocc='' acl='' type='string'></node>
                <node name='MACAddress' rw='0' getc='0' noc='0' nocc='' acl='' type='string'></node>
                <node name='MaxBitRate' rw='1' getc='0' noc='0' nocc='' acl='Subscriber' type='string'></node>
                <node name='DuplexMode' rw='1' getc='0' noc='0' nocc='' acl='Subscriber' type='string'></node>
                <node name='Stats' rw='0' type='node'>
                    <node name='BytesSent' rw='0' getc='0' noc='0' nocc='' acl='' type='unsignedInt'></node>
                    <node name='BytesReceived' rw='0' getc='0' noc='0' nocc='' acl='' type='unsignedInt'></node>
                    <node name='PacketsSent' rw='0' getc='0' noc='0' nocc='' acl='' type='unsignedInt'></node>
                    <node name='PacketsReceived' rw='0' getc='0' noc='0' nocc='' acl='' type='unsignedInt'></node>
                </node>
            </node>
        </node>
    </node>
    <node name='Time' rw='0' type='node'>
        <node name='NTPServer1' rw='1' getc='0' noc='0' nocc='' acl='Subscriber' type='string'></node>
        <node name='NTPServer2' rw='1' getc='0' noc='0' nocc='' acl='Subscriber' type='string'></node>
        <node name='CurrentLocalTime' rw='1' getc='0' noc='0' nocc='' acl='' type='dateTime'></node>
        <node name='LocalTimeZone' rw='1' getc='0' noc='0' nocc='' acl='Subscriber' type='string'></node>
        <node name='LocalTimeZoneName' rw='1' getc='0' noc='0' nocc='' acl='Subscriber' type='string'></node>
        <node name='DaylightSavingsUsed' rw='1' getc='0' noc='0' nocc='' acl='Subscriber' type='boolean'></node>
        <node name='DaylightSavingsStart' rw='1' getc='0' noc='0' nocc='' acl='Subscriber' type='dateTime'></node>
        <node name='DaylightSavingsEnd' rw='1' getc='0' noc='0' nocc='' acl='Subscriber' type='dateTime'></node>
    </node>
    <node name='IPPingDiagnostics' rw='0' type='node'>
        <node name='DiagnosticsState' rw='1' getc='0' noc='0' nocc='' acl='Subscriber' type='string'>None</node>
        <node name='Interface' rw='1' getc='0' noc='0' nocc='' acl='Subscriber' type='string'></node>
        <node name='Host' rw='1' getc='0' noc='0' nocc='' acl='Subscriber' type='string'></node>
        <node name='NumberOfRepetitions' rw='1' getc='0' noc='0' nocc='' acl='Subscriber' type='unsignedInt'></node>
        <node name='Timeout' rw='1' getc='0' noc='0' nocc='' acl='Subscriber' type='unsignedInt'></node>
        <node name='DataBlockSize' rw='1' getc='0' noc='0' nocc='' acl='Subscriber' type='unsignedInt'></node>
        <node name='DSCP' rw='1' getc='0' noc='0' nocc='' acl='Subscriber' type='unsignedInt'></node>
        <node name='SuccessCount' rw='0' getc='0' noc='0' nocc='' acl='' type='unsignedInt'></node>
        <node name='FailureCount' rw='0' getc='0' noc='0' nocc='' acl='' type='unsignedInt'></node>
        <node name='AverageResponseTime' rw='0' getc='0' noc='0' nocc='' acl='' type='unsignedInt'></node>
        <node name='MinimumResponseTime' rw='0' getc='0' noc='0' nocc='' acl='' type='unsignedInt'></node>
        <node name='MaximumResponseTime' rw='0' getc='0' noc='0' nocc='' acl='' type='unsignedInt'></node>
    </node>
    <node name='X_CT-COM_UplinkQoS' rw='0' type='node'>
        <node name='Mode' rw='1' getc='0' noc='0' nocc='' acl='Subscriber' type='string'></node>
        <node name='Enable' rw='1' getc='0' noc='0' nocc='' acl='Subscriber' type='boolean'></node>
        <node name='Bandwidth' rw='1' getc='0' noc='0' nocc='' acl='Subscriber' type='unsignedInt'></node>
        <node name='Plan' rw='1' getc='0' noc='0' nocc='' acl='Subscriber' type='string'></node>
        <node name='EnableForceWeight' rw='1' getc='0' noc='0' nocc='' acl='Subscriber' type='boolean'></node>
        <node name='EnableDSCPMark' rw='1' getc='0' noc='0' nocc='' acl='Subscriber' type='boolean'></node>
        <node name='Enable802-1_P' rw='1' getc='0' noc='0' nocc='' acl='Subscriber' type='unsignedInt'></node>
        <node name='App' rw='1' nin='1' il='9' type='node'>
            <node name='template' rw='1' nin='0' il='0' type='node'>
                <node name='AppName' rw='1' getc='0' noc='0' nocc='' acl='Subscriber' type='string'></node>
                <node name='ClassQueue' rw='1' getc='0' noc='0' nocc='' acl='Subscriber' type='unsignedInt'></node>
            </node>
        </node> 
        <node name='Classification' rw='1' nin='1' il='9' type='node'>
            <node name='template' rw='1' nin='0' il='0' type='node'>
                <node name='ClassQueue' rw='1' getc='0' noc='0' nocc='' acl='Subscriber' type='unsignedInt'></node>
                <node name='DSCPMarkValue' rw='1' getc='0' noc='0' nocc='' acl='Subscriber' type='unsignedInt'></node>
                <node name='802-1_P_Value' rw='1' getc='0' noc='0' nocc='' acl='Subscriber' type='unsignedInt'></node>
                <node name='type' rw='1' nin='1' il='9' type='node'>
                    <node name='template' rw='1' nin='0' il='0' type='node'>
                        <node name='Type' rw='1' getc='0' noc='0' nocc='' acl='Subscriber' type='string'></node>
                        <node name='Max' rw='1' getc='0' noc='0' nocc='' acl='Subscriber' type='string'></node>
                        <node name='Min' rw='1' getc='0' noc='0' nocc='' acl='Subscriber' type='string'></node>
                        <node name='ProtocolList' rw='1' getc='0' noc='0' nocc='' acl='Subscriber' type='string'></node>
                    </node>
                </node>    
            </node>
        </node> 
        <node name='PriorityQueue' rw='1' nin='1' il='6' type='node'>
        	<node name='template' rw='1' nin='0' il='0' type='node'>
                <node name='Enable' rw='1' getc='0' noc='0' nocc='' acl='Subscriber' type='boolean'></node>
                <node name='Priority' rw='1' getc='0' noc='0' nocc='' acl='Subscriber' type='unsignedInt'></node>
                <node name='Weight' rw='1' getc='0' noc='0' nocc='' acl='Subscriber' type='unsignedInt'></node>
            </node>
        </node>                                  
    </node>    
    <node name='X_CT-COM_UserInfo' rw='0' type='node'>
        <node name='UserName' rw='0' getc='0' noc='0' nocc='' acl='' type='string'></node>
        <node name='UserId' rw='0' getc='0' noc='0' nocc='' acl='' type='string'></node>
        <node name='Status' rw='1' getc='0' noc='0' nocc='' acl='Subscriber' type='unsignedInt' forceset='1'></node>
        <node name='Limit' rw='1' getc='0' noc='0' nocc='' acl='Subscriber' type='unsignedInt'></node>
        <node name='Times' rw='1' getc='0' noc='0' nocc='' acl='Subscriber' type='unsignedInt'></node>
        <node name='Result' rw='1' getc='0' noc='0' nocc='' acl='Subscriber' type='unsignedInt'></node>
    </node>
<!--    
    <node name='Services' rw='0' type='node'>
        <node name='X_CT-COM_IPTV' rw='0' type='node'>
            <node name='IGMPEnable' rw='1' getc='0' noc='0' nocc='' acl='Subscriber' type='boolean'>false</node>
            <node name='ProxyEnable' rw='1' getc='0' noc='0' nocc='' acl='Subscriber' type='boolean'>true</node>
            <node name='SnoopingEnable' rw='1' getc='0' noc='0' nocc='' acl='Subscriber' type='boolean'>true</node>
            <node name='STBNumber' rw='0' getc='0' noc='0' nocc='' acl='' type='unsignedInt'></node>
        </node>
        <node name='X_CT-COM_MWBAND' rw='0' type='node'>
            <node name='Mode' rw='1' getc='0' noc='0' nocc='' acl='Subscriber' type='int'>1</node>
            <node name='TotalTerminalNumber' rw='1' getc='0' noc='0' nocc='' acl='Subscriber' type='int'>4</node>
            <node name='STBRestrictEnable' rw='1' getc='0' noc='0' nocc='' acl='Subscriber' type='boolean'>false</node>
            <node name='STBNumber' rw='1' getc='0' noc='0' nocc='' acl='Subscriber' type='int'>-1</node>
            <node name='CameraRestrictEnable' rw='1' getc='0' noc='0' nocc='' acl='Subscriber' type='boolean'>false</node>
            <node name='CameraNumber' rw='1' getc='0' noc='0' nocc='' acl='Subscriber' type='int'></node>
            <node name='ComputerRestrictEnable' rw='1' getc='0' noc='0' nocc='' acl='Subscriber' type='boolean'>flase</node>
            <node name='ComputerNumber' rw='1' getc='0' noc='0' nocc='' acl='Subscriber' type='int'>1</node>
            <node name='PhoneRestrictEnable' rw='1' getc='0' noc='0' nocc='' acl='Subscriber' type='boolean'>false</node>
            <node name='PhoneNumber' rw='1' getc='0' noc='0' nocc='' acl='Subscriber' type='int'>-1</node>
        </node>
    </node>
-->
</node>
